setup.py
dm/__init__.py
dm.transaction.aborthook.egg-info/PKG-INFO
dm.transaction.aborthook.egg-info/SOURCES.txt
dm.transaction.aborthook.egg-info/dependency_links.txt
dm.transaction.aborthook.egg-info/namespace_packages.txt
dm.transaction.aborthook.egg-info/not-zip-safe
dm.transaction.aborthook.egg-info/top_level.txt
dm/transaction/__init__.py
dm/transaction/aborthook/README.txt
dm/transaction/aborthook/VERSION.txt
dm/transaction/aborthook/__init__.py