Metadata-Version: 1.0
Name: dm.transaction.aborthook
Version: 1.0
Summary: Patch `transaction` to support abort hooks
Home-page: http://pypi.python.org/pypi/dm.transaction.aborthook
Author: Dieter Maurer
Author-email: dieter@handshake.de
License: ZPL
Keywords: ZODB recovery
Platform: UNKNOWN
Classifier: Development Status :: 5 - Production/Stable
Classifier: Intended Audience :: Developers
Classifier: License :: OSI Approved :: Zope Public License
Classifier: Framework :: Zope2
Classifier: Operating System :: OS Independent
Classifier: Programming Language :: Python
Classifier: Topic :: Utilities
